qencode/__init__.py
qencode/client.py
qencode/const.py
qencode/custom_params.py
qencode/exeptions.py
qencode/httptools.py
qencode/metadata.py
qencode/task.py
qencode/tools.py
qencode/tus_uploader.py
qencode/utils.py
qencode/drm/__init__.py
qencode/drm/buydrm.py
qencode/drm/keys/buydrm_qencode_public_cert.pem
qencode-1.0.4.dist-info/LICENSE
qencode-1.0.4.dist-info/METADATA
qencode-1.0.4.dist-info/WHEEL
qencode-1.0.4.dist-info/top_level.txt
qencode-1.0.4.dist-info/RECORD
