Metadata-Version: 2.1
Name: qencode
Version: 1.0.4
Summary: Client library for main features and functionality of Qencode for Python v2.x.
Home-page: https://github.com/qencode-dev/qencode-api-python-client
Author: Qencode Developer
Author-email: team@qencode.com
License: proprietary
Keywords: qencode,qencode.com,cloud.qencode.com
Platform: UNKNOWN
Classifier: Development Status :: 5 - Production/Stable
Classifier: Intended Audience :: Developers
Classifier: Topic :: Software Development :: Build Tools
Classifier: License :: Other/Proprietary License
Classifier: Programming Language :: Python :: 2.7
